twoaxistracking/__init__.py
twoaxistracking/layout.py
twoaxistracking/plotting.py
twoaxistracking/shading.py
twoaxistracking/trackerfield.py
twoaxistracking-0.2.5.dist-info/LICENSE
twoaxistracking-0.2.5.dist-info/METADATA
twoaxistracking-0.2.5.dist-info/WHEEL
twoaxistracking-0.2.5.dist-info/top_level.txt
twoaxistracking-0.2.5.dist-info/RECORD
