Metadata-Version: 2.1
Name: twoaxistracking
Version: 0.2.5
Summary: twoaxistracking is a python package for simulating two-axis tracking solar collectors, particularly self-shading.
Home-page: https://github.com/pvlib/twoaxistracking
Author: 'Adam R. Jensen, Kevin Anderson'
Author-email: adam-r-j@hotmail.com
Project-URL: Bug Tracker, https://github.com/pvlib/twoaxistracking/issues
Project-URL: Documentation, https://twoaxistracking.readthedocs.io
Classifier: Programming Language :: Python :: 3
Classifier: License :: OSI Approved :: BSD License
Classifier: Operating System :: OS Independent
Classifier: Topic :: Scientific/Engineering
Classifier: Intended Audience :: Science/Research
Requires-Python: >=3.9
License-File: LICENSE
Requires-Dist: numpy
Requires-Dist: matplotlib
Requires-Dist: shapely
Requires-Dist: pandas
Provides-Extra: doc
Requires-Dist: sphinx==8.1.1; extra == "doc"
Requires-Dist: myst-nb==1.1.2; extra == "doc"
Requires-Dist: sphinx-book-theme==1.1.3; extra == "doc"
Requires-Dist: pvlib==0.11.1; extra == "doc"
Requires-Dist: pandas==2.2.3; extra == "doc"
Provides-Extra: test
Requires-Dist: pytest; extra == "test"
Requires-Dist: pytest-cov; extra == "test"
Requires-Dist: packaging; extra == "test"
